rift/__about__.py
rift/__init__.py
rift/__main__.py
rift/agents/__init__.py
rift/llm/__init__.py
rift/llm/abstract.py
rift/llm/create.py
rift/llm/gpt4all_model.py
rift/llm/hf_client.py
rift/llm/openai_client.py
rift/llm/openai_types.py
rift/lsp/__init__.py
rift/lsp/document.py
rift/lsp/server.py
rift/lsp/types.py
rift/rpc/__init__.py
rift/rpc/extrarpc.py
rift/rpc/io_transport.py
rift/rpc/jsonrpc.py
rift/rpc/transport.py
rift/server/__init__.py
rift/server/core.py
rift/server/helper.py
rift/server/lsp.py
rift/server/selection.py
rift/util/TextStream.py
rift/util/__init__.py
rift/util/asyncgen.py
rift/util/dispatch.py
rift/util/misc.py
rift/util/ofdict.py
rift/util/type_util.py
pyrift-0.0.6.dist-info/METADATA
pyrift-0.0.6.dist-info/WHEEL
pyrift-0.0.6.dist-info/entry_points.txt
pyrift-0.0.6.dist-info/RECORD
