Metadata-Version: 2.1
Name: pyrift
Version: 0.0.6
Project-URL: Documentation, https://github.com/morph-labs/rift#readme
Project-URL: Issues, https://github.com/morph-labs/rift/issues
Project-URL: Source, https://github.com/morph-labs/rift
Author-email: Morph Labs <support@morph.so>
Requires-Python: >=3.9
Requires-Dist: aiohttp
Requires-Dist: fire
Requires-Dist: gpt4all==0.3.4
Requires-Dist: pydantic[dotenv]==1.*
Requires-Dist: python-dotenv
Requires-Dist: rich
Requires-Dist: sentencepiece
Requires-Dist: tiktoken
Requires-Dist: transformers
Provides-Extra: hf
Requires-Dist: torch; extra == 'hf'
